<?xml version="1.0" encoding="utf-8"?>
<!--Use like this: <Include File="WorldTrackerCivic"/>-->
<Root xmlns:xsi="http://www.w3.org/2001/XMLSchema-instance" xsi:noNamespaceSchemaLocation="..\..\..\..\..\CivTech\Libs\ForgeUI\ForgeUI_Assets\Controls.xsd">

	<Instance						Name="CivicInstance">
		<Grid							ID="MainPanel"																Offset="0,0"		Size="296,28"					Texture="CivicPanel_Frame" SliceCorner="80,80" SliceSize="1,1" SliceTextureSize="110,88" ConsumeMouseOver="1">
			<!-- <Box																													Offset="0,25"		Size="parent,1" 			Color="0,0,0,100"/> -->

			<Container			ID="HeaderButton"															Offset="0,0"		Size="parent,parent" >
				<Button				ID="IconButton"																Offset="-5,0"													Texture="CivicPanel_MeterFrame" >
					<Button			ID="IconButtonInner"						Anchor="C,C"									Size="11,11"					Texture="CivicPanel_Button" >
						<Image		ID="Icon"												Anchor="C,C"									Size="9,9"						Texture="Tech38" />
					</Button>
					<Meter			ID="BoostMeter"									Anchor="C,C"									Size="14,14"					Texture="CivicPanel_BoostMeter" Percent="0"		Speed="1.0" Follow="1"/>
					<Meter			ID="ProgressMeter"							Anchor="C,C"									Size="14,14"					Texture="CivicPanel_Meter" 		Percent=".4"	Speed="1.0" Follow="1"/>
          <FlipAnim		ID="MainGearAnim"															Offset="0,0"													Texture="CivicPanel_MeterFrameAnim" FrameCount="3" Columns="3" Speed="10" Size="10,10" Stopped="1" Hidden="0"/>
				</Image>

				<TextButton		ID="TitleButton"															Offset="65,6"		Size="200,20"					Style="PanelHeaderText" String="Civic_CQUI" />
				<Label				ID="TurnsLeft"									Anchor="R,T"	Offset="5,6"		Style="FontNormal14"	String="33" />
			</Container>

			<Container			ID="Removed"																	Offset="0,0"		Size="parent,parent"	Hidden="1" >
				<Label				ID="TurnsLeftLabel"							Anchor="L,T"	Offset="2,0" 	Style="FontNormal12"	String="LOC_RESEARCH_CHOOSER_TURNS" Hidden="1" />
				<Image				ID="IconCanBeBoosted"						Anchor="L,B"	Offset="50,-4"												Texture="CivicPanel_BoostIconAvailable"	Hidden="1" />
				<Label				ID="BoostLabel"									Anchor="L,B"	Offset="80,7"		Style="FontNormal12"	Color0="150,150,150,155" />
				<Image				ID="IconHasBeenBoosted"					Anchor="L,B"	Offset="50,-4"												Texture="CivicPanel_BoostIconBoosted"		Hidden="1" />
				<Stack				ID="UnlockStack"															Offset="65,0"	StackGrowth="Right" StackPadding="-2" Hidden="1" />
        <Button   ID="UnlockPageTurner"   Anchor="R,B"   Offset="18, 33"  Size ="19,0" Hidden="1" >
          <Image  ID="PageTurnerImage"    Anchor="C,C"   Offset="0,0"     Size="parent,parent"  Texture="Controls_ArrowButtonRight" FlipX="false"/>
        </Button>
			</Container>

		</Grid>
	</Instance>

</Root>